[
  {
    "dex": 1,
    "nameFR": "Bulbizarre",
    "types": []
  },
  {
    "dex": 2,
    "nameFR": "Herbizarre",
    "types": []
  },
  {
    "dex": 3,
    "nameFR": "Florizarre",
    "types": []
  },
  {
    "dex": 4,
    "nameFR": "Salamèche",
    "types": []
  },
  {
    "dex": 5,
    "nameFR": "Reptincel",
    "types": []
  },
  {
    "dex": 6,
    "nameFR": "Dracaufeu",
    "types": []
  },
  {
    "dex": 7,
    "nameFR": "Carapuce",
    "types": []
  },
  {
    "dex": 8,
    "nameFR": "Carabaffe",
    "types": []
  },
  {
    "dex": 9,
    "nameFR": "Tortank",
    "types": []
  },
  {
    "dex": 10,
    "nameFR": "Chenipan",
    "types": []
  }
]